cwrap/__init__.py
cwrap/basecclass.py
cwrap/basecenum.py
cwrap/basecvalue.py
cwrap/cfile.py
cwrap/clib.py
cwrap/metacwrap.py
cwrap/prototype.py
cwrap/version.py
cwrap-1.6.11.dist-info/licenses/LICENSE
cwrap-1.6.11.dist-info/METADATA
cwrap-1.6.11.dist-info/WHEEL
cwrap-1.6.11.dist-info/top_level.txt
cwrap-1.6.11.dist-info/RECORD
